{"precinct":"107th Precinct","month":"     May","violations":[{"name":"Backing Unsafely","mtd":1,"ytd":2},{"name":"Brake Lights (Defect.or Improper)","mtd":60,"ytd":279},{"name":"Bus Lane, Driving in","mtd":0,"ytd":0},{"name":"Cell Phone","mtd":148,"ytd":606},{"name":"Commercial Veh on Pkwy","mtd":0,"ytd":0},{"name":"Defective Brakes","mtd":0,"ytd":0},{"name":"Disobey Sign","mtd":203,"ytd":816},{"name":"Equipment (Other)","mtd":3,"ytd":4},{"name":"Fail to Keep Right","mtd":0,"ytd":0},{"name":"Fail to Signal","mtd":3,"ytd":3},{"name":"Fail to Stop on Signal","mtd":14,"ytd":35},{"name":"Following Too Closely","mtd":0,"ytd":1},{"name":"Headlights (Defect. or Improper)","mtd":33,"ytd":203},{"name":"Improper Lights","mtd":0,"ytd":5},{"name":"Improper Passing","mtd":5,"ytd":18},{"name":"Improper Turn","mtd":198,"ytd":1148},{"name":"Improper/Missing Plates","mtd":0,"ytd":0},{"name":"Not Giving R of W to Pedes.","mtd":3,"ytd":39},{"name":"Not Giving R of W to Veh.","mtd":3,"ytd":76},{"name":"One Way Street","mtd":1,"ytd":2},{"name":"Pavement Markings","mtd":8,"ytd":130},{"name":"Safety Belt","mtd":246,"ytd":1058},{"name":"School Bus, Passing Stopped","mtd":0,"ytd":0},{"name":"Speeding","mtd":22,"ytd":109},{"name":"Spillback","mtd":0,"ytd":4},{"name":"Tinted Windows","mtd":55,"ytd":315},{"name":"Truck Routes","mtd":9,"ytd":15},{"name":"U-Turn","mtd":0,"ytd":0},{"name":"Uninspected","mtd":6,"ytd":32},{"name":"Uninsured","mtd":39,"ytd":158},{"name":"Unlicensed Operator","mtd":87,"ytd":369},{"name":"Unregistered","mtd":9,"ytd":24},{"name":"Unsafe Lane Change","mtd":0,"ytd":7},{"name":"Other Movers","mtd":12,"ytd":81}]}