{"precinct":"108th Precinct","month":"    July","violations":[{"name":"Backing Unsafely","mtd":0,"ytd":1},{"name":"Brake Lights (Defect.or Improper)","mtd":19,"ytd":206},{"name":"Bus Lane, Driving in","mtd":0,"ytd":0},{"name":"Cell Phone","mtd":184,"ytd":912},{"name":"Commercial Veh on Pkwy","mtd":0,"ytd":0},{"name":"Defective Brakes","mtd":0,"ytd":8},{"name":"Disobey Sign","mtd":353,"ytd":1621},{"name":"Equipment (Other)","mtd":0,"ytd":1},{"name":"Fail to Keep Right","mtd":0,"ytd":0},{"name":"Fail to Signal","mtd":5,"ytd":86},{"name":"Fail to Stop on Signal","mtd":34,"ytd":396},{"name":"Following Too Closely","mtd":0,"ytd":3},{"name":"Headlights (Defect. or Improper)","mtd":0,"ytd":12},{"name":"Improper Lights","mtd":0,"ytd":0},{"name":"Improper Passing","mtd":0,"ytd":2},{"name":"Improper Turn","mtd":93,"ytd":933},{"name":"Improper/Missing Plates","mtd":1,"ytd":10},{"name":"Not Giving R of W to Pedes.","mtd":4,"ytd":200},{"name":"Not Giving R of W to Veh.","mtd":0,"ytd":13},{"name":"One Way Street","mtd":3,"ytd":12},{"name":"Pavement Markings","mtd":5,"ytd":224},{"name":"Safety Belt","mtd":166,"ytd":1096},{"name":"School Bus, Passing Stopped","mtd":0,"ytd":6},{"name":"Speeding","mtd":37,"ytd":271},{"name":"Spillback","mtd":0,"ytd":9},{"name":"Tinted Windows","mtd":119,"ytd":369},{"name":"Truck Routes","mtd":71,"ytd":163},{"name":"U-Turn","mtd":1,"ytd":3},{"name":"Uninspected","mtd":2,"ytd":24},{"name":"Uninsured","mtd":60,"ytd":417},{"name":"Unlicensed Operator","mtd":107,"ytd":510},{"name":"Unregistered","mtd":10,"ytd":38},{"name":"Unsafe Lane Change","mtd":0,"ytd":4},{"name":"Other Movers","mtd":139,"ytd":700}]}