{"precinct":"83rd Precinct","month":"November","violations":[{"name":"Backing Unsafely","mtd":4,"ytd":47},{"name":"Brake Lights (Defect.or Improper)","mtd":27,"ytd":302},{"name":"Bus Lane, Driving in","mtd":0,"ytd":0},{"name":"Cell Phone","mtd":84,"ytd":1295},{"name":"Commercial Veh on Pkwy","mtd":0,"ytd":5},{"name":"Defective Brakes","mtd":10,"ytd":19},{"name":"Disobey Sign","mtd":310,"ytd":2596},{"name":"Equipment (Other)","mtd":1,"ytd":40},{"name":"Fail to Keep Right","mtd":0,"ytd":11},{"name":"Fail to Signal","mtd":34,"ytd":576},{"name":"Fail to Stop on Signal","mtd":40,"ytd":720},{"name":"Following Too Closely","mtd":0,"ytd":7},{"name":"Headlights (Defect. or Improper)","mtd":18,"ytd":239},{"name":"Improper Lights","mtd":1,"ytd":46},{"name":"Improper Passing","mtd":3,"ytd":30},{"name":"Improper Turn","mtd":27,"ytd":47},{"name":"Improper/Missing Plates","mtd":1,"ytd":34},{"name":"Not Giving R of W to Pedes.","mtd":7,"ytd":56},{"name":"Not Giving R of W to Veh.","mtd":5,"ytd":26},{"name":"One Way Street","mtd":8,"ytd":66},{"name":"Pavement Markings","mtd":6,"ytd":109},{"name":"Safety Belt","mtd":40,"ytd":752},{"name":"School Bus, Passing Stopped","mtd":2,"ytd":10},{"name":"Speeding","mtd":3,"ytd":23},{"name":"Spillback","mtd":0,"ytd":1},{"name":"Tinted Windows","mtd":9,"ytd":281},{"name":"Truck Routes","mtd":11,"ytd":112},{"name":"U-Turn","mtd":2,"ytd":28},{"name":"Uninspected","mtd":3,"ytd":48},{"name":"Uninsured","mtd":60,"ytd":1013},{"name":"Unlicensed Operator","mtd":81,"ytd":1467},{"name":"Unregistered","mtd":15,"ytd":224},{"name":"Unsafe Lane Change","mtd":0,"ytd":7},{"name":"Other Movers","mtd":7,"ytd":216}]}