{"precinct":"33rd Precinct","month":"November","violations":[{"name":"Backing Unsafely","mtd":0,"ytd":11},{"name":"Brake Lights (Defect.or Improper)","mtd":20,"ytd":307},{"name":"Bus Lane, Driving in","mtd":0,"ytd":1},{"name":"Cell Phone","mtd":101,"ytd":1393},{"name":"Commercial Veh on Pkwy","mtd":0,"ytd":18},{"name":"Defective Brakes","mtd":1,"ytd":5},{"name":"Disobey Sign","mtd":76,"ytd":372},{"name":"Equipment (Other)","mtd":1,"ytd":46},{"name":"Fail to Keep Right","mtd":0,"ytd":8},{"name":"Fail to Signal","mtd":9,"ytd":97},{"name":"Fail to Stop on Signal","mtd":23,"ytd":259},{"name":"Following Too Closely","mtd":0,"ytd":2},{"name":"Headlights (Defect. or Improper)","mtd":12,"ytd":219},{"name":"Improper Lights","mtd":0,"ytd":2},{"name":"Improper Passing","mtd":1,"ytd":3},{"name":"Improper Turn","mtd":8,"ytd":111},{"name":"Improper/Missing Plates","mtd":5,"ytd":30},{"name":"Not Giving R of W to Pedes.","mtd":65,"ytd":269},{"name":"Not Giving R of W to Veh.","mtd":0,"ytd":4},{"name":"One Way Street","mtd":2,"ytd":33},{"name":"Pavement Markings","mtd":1,"ytd":16},{"name":"Safety Belt","mtd":56,"ytd":1031},{"name":"School Bus, Passing Stopped","mtd":3,"ytd":17},{"name":"Speeding","mtd":27,"ytd":407},{"name":"Spillback","mtd":0,"ytd":4},{"name":"Tinted Windows","mtd":31,"ytd":379},{"name":"Truck Routes","mtd":21,"ytd":161},{"name":"U-Turn","mtd":9,"ytd":171},{"name":"Uninspected","mtd":0,"ytd":17},{"name":"Uninsured","mtd":31,"ytd":283},{"name":"Unlicensed Operator","mtd":18,"ytd":209},{"name":"Unregistered","mtd":7,"ytd":100},{"name":"Unsafe Lane Change","mtd":2,"ytd":15},{"name":"Other Movers","mtd":48,"ytd":430}]}