{"precinct":"41st Precinct","month":"February","violations":[{"name":"Backing Unsafely","mtd":1,"ytd":2},{"name":"Brake Lights (Defect.or Improper)","mtd":10,"ytd":33},{"name":"Bus Lane, Driving in","mtd":0,"ytd":0},{"name":"Cell Phone","mtd":23,"ytd":50},{"name":"Commercial Veh on Pkwy","mtd":0,"ytd":0},{"name":"Defective Brakes","mtd":0,"ytd":0},{"name":"Disobey Sign","mtd":156,"ytd":280},{"name":"Equipment (Other)","mtd":8,"ytd":19},{"name":"Fail to Keep Right","mtd":0,"ytd":0},{"name":"Fail to Signal","mtd":12,"ytd":22},{"name":"Fail to Stop on Signal","mtd":33,"ytd":72},{"name":"Following Too Closely","mtd":1,"ytd":1},{"name":"Headlights (Defect. or Improper)","mtd":38,"ytd":68},{"name":"Improper Lights","mtd":1,"ytd":5},{"name":"Improper Passing","mtd":1,"ytd":1},{"name":"Improper Turn","mtd":58,"ytd":115},{"name":"Improper/Missing Plates","mtd":7,"ytd":10},{"name":"Not Giving R of W to Pedes.","mtd":1,"ytd":1},{"name":"Not Giving R of W to Veh.","mtd":1,"ytd":1},{"name":"One Way Street","mtd":5,"ytd":7},{"name":"Pavement Markings","mtd":7,"ytd":16},{"name":"Safety Belt","mtd":41,"ytd":52},{"name":"School Bus, Passing Stopped","mtd":0,"ytd":0},{"name":"Speeding","mtd":35,"ytd":94},{"name":"Spillback","mtd":0,"ytd":0},{"name":"Tinted Windows","mtd":39,"ytd":83},{"name":"Truck Routes","mtd":3,"ytd":4},{"name":"U-Turn","mtd":8,"ytd":29},{"name":"Uninspected","mtd":7,"ytd":15},{"name":"Uninsured","mtd":71,"ytd":140},{"name":"Unlicensed Operator","mtd":43,"ytd":94},{"name":"Unregistered","mtd":10,"ytd":24},{"name":"Unsafe Lane Change","mtd":2,"ytd":3},{"name":"Other Movers","mtd":10,"ytd":15}]}