{"precinct":"Transportation Bureau","month":"   April","violations":[{"name":"Backing Unsafely","mtd":10,"ytd":29},{"name":"Brake Lights (Defect.or Improper)","mtd":69,"ytd":186},{"name":"Bus Lane, Driving in","mtd":706,"ytd":2334},{"name":"Cell Phone","mtd":1016,"ytd":4057},{"name":"Commercial Veh on Pkwy","mtd":54,"ytd":239},{"name":"Defective Brakes","mtd":0,"ytd":1},{"name":"Disobey Sign","mtd":3135,"ytd":13466},{"name":"Equipment (Other)","mtd":602,"ytd":1728},{"name":"Fail to Keep Right","mtd":0,"ytd":13},{"name":"Fail to Signal","mtd":332,"ytd":1265},{"name":"Fail to Stop on Signal","mtd":388,"ytd":1675},{"name":"Following Too Closely","mtd":64,"ytd":258},{"name":"Headlights (Defect. or Improper)","mtd":30,"ytd":110},{"name":"Improper Lights","mtd":3,"ytd":16},{"name":"Improper Passing","mtd":284,"ytd":803},{"name":"Improper Turn","mtd":1796,"ytd":4972},{"name":"Improper/Missing Plates","mtd":7,"ytd":34},{"name":"Not Giving R of W to Pedes.","mtd":70,"ytd":241},{"name":"Not Giving R of W to Veh.","mtd":54,"ytd":120},{"name":"One Way Street","mtd":34,"ytd":58},{"name":"Pavement Markings","mtd":298,"ytd":1038},{"name":"Safety Belt","mtd":633,"ytd":2367},{"name":"School Bus, Passing Stopped","mtd":15,"ytd":32},{"name":"Speeding","mtd":6111,"ytd":20610},{"name":"Spillback","mtd":156,"ytd":456},{"name":"Tinted Windows","mtd":1863,"ytd":6358},{"name":"Truck Routes","mtd":9,"ytd":39},{"name":"U-Turn","mtd":1,"ytd":7},{"name":"Uninspected","mtd":116,"ytd":412},{"name":"Uninsured","mtd":259,"ytd":889},{"name":"Unlicensed Operator","mtd":485,"ytd":1730},{"name":"Unregistered","mtd":107,"ytd":386},{"name":"Unsafe Lane Change","mtd":111,"ytd":407},{"name":"Other Movers","mtd":3699,"ytd":11321}]}