{"precinct":"107th Precinct","month":"   April","violations":[{"name":"Backing Unsafely","mtd":1,"ytd":1},{"name":"Brake Lights (Defect.or Improper)","mtd":60,"ytd":219},{"name":"Bus Lane, Driving in","mtd":0,"ytd":0},{"name":"Cell Phone","mtd":107,"ytd":458},{"name":"Commercial Veh on Pkwy","mtd":0,"ytd":0},{"name":"Defective Brakes","mtd":0,"ytd":0},{"name":"Disobey Sign","mtd":187,"ytd":613},{"name":"Equipment (Other)","mtd":0,"ytd":1},{"name":"Fail to Keep Right","mtd":0,"ytd":0},{"name":"Fail to Signal","mtd":0,"ytd":0},{"name":"Fail to Stop on Signal","mtd":4,"ytd":21},{"name":"Following Too Closely","mtd":0,"ytd":1},{"name":"Headlights (Defect. or Improper)","mtd":28,"ytd":170},{"name":"Improper Lights","mtd":0,"ytd":5},{"name":"Improper Passing","mtd":5,"ytd":13},{"name":"Improper Turn","mtd":355,"ytd":950},{"name":"Improper/Missing Plates","mtd":0,"ytd":0},{"name":"Not Giving R of W to Pedes.","mtd":15,"ytd":36},{"name":"Not Giving R of W to Veh.","mtd":15,"ytd":73},{"name":"One Way Street","mtd":0,"ytd":1},{"name":"Pavement Markings","mtd":39,"ytd":122},{"name":"Safety Belt","mtd":239,"ytd":812},{"name":"School Bus, Passing Stopped","mtd":0,"ytd":0},{"name":"Speeding","mtd":18,"ytd":87},{"name":"Spillback","mtd":0,"ytd":4},{"name":"Tinted Windows","mtd":58,"ytd":260},{"name":"Truck Routes","mtd":6,"ytd":6},{"name":"U-Turn","mtd":0,"ytd":0},{"name":"Uninspected","mtd":8,"ytd":26},{"name":"Uninsured","mtd":23,"ytd":119},{"name":"Unlicensed Operator","mtd":82,"ytd":282},{"name":"Unregistered","mtd":4,"ytd":15},{"name":"Unsafe Lane Change","mtd":1,"ytd":7},{"name":"Other Movers","mtd":19,"ytd":69}]}