{"precinct":"113th Precinct","month":"   April","violations":[{"name":"Backing Unsafely","mtd":1,"ytd":8},{"name":"Brake Lights (Defect.or Improper)","mtd":74,"ytd":345},{"name":"Bus Lane, Driving in","mtd":0,"ytd":0},{"name":"Cell Phone","mtd":147,"ytd":526},{"name":"Commercial Veh on Pkwy","mtd":0,"ytd":0},{"name":"Defective Brakes","mtd":0,"ytd":4},{"name":"Disobey Sign","mtd":53,"ytd":272},{"name":"Equipment (Other)","mtd":110,"ytd":217},{"name":"Fail to Keep Right","mtd":0,"ytd":0},{"name":"Fail to Signal","mtd":6,"ytd":8},{"name":"Fail to Stop on Signal","mtd":73,"ytd":235},{"name":"Following Too Closely","mtd":0,"ytd":0},{"name":"Headlights (Defect. or Improper)","mtd":0,"ytd":30},{"name":"Improper Lights","mtd":0,"ytd":3},{"name":"Improper Passing","mtd":2,"ytd":9},{"name":"Improper Turn","mtd":156,"ytd":685},{"name":"Improper/Missing Plates","mtd":3,"ytd":7},{"name":"Not Giving R of W to Pedes.","mtd":1,"ytd":3},{"name":"Not Giving R of W to Veh.","mtd":1,"ytd":3},{"name":"One Way Street","mtd":0,"ytd":0},{"name":"Pavement Markings","mtd":13,"ytd":70},{"name":"Safety Belt","mtd":82,"ytd":282},{"name":"School Bus, Passing Stopped","mtd":1,"ytd":3},{"name":"Speeding","mtd":5,"ytd":44},{"name":"Spillback","mtd":0,"ytd":2},{"name":"Tinted Windows","mtd":526,"ytd":1814},{"name":"Truck Routes","mtd":14,"ytd":15},{"name":"U-Turn","mtd":1,"ytd":1},{"name":"Uninspected","mtd":8,"ytd":54},{"name":"Uninsured","mtd":94,"ytd":358},{"name":"Unlicensed Operator","mtd":126,"ytd":494},{"name":"Unregistered","mtd":26,"ytd":83},{"name":"Unsafe Lane Change","mtd":0,"ytd":1},{"name":"Other Movers","mtd":31,"ytd":171}]}