{"precinct":"113th Precinct","month":"Septembe","violations":[{"name":"Backing Unsafely","mtd":1,"ytd":18},{"name":"Brake Lights (Defect.or Improper)","mtd":70,"ytd":648},{"name":"Bus Lane, Driving in","mtd":0,"ytd":0},{"name":"Cell Phone","mtd":154,"ytd":1144},{"name":"Commercial Veh on Pkwy","mtd":0,"ytd":0},{"name":"Defective Brakes","mtd":0,"ytd":4},{"name":"Disobey Sign","mtd":114,"ytd":745},{"name":"Equipment (Other)","mtd":197,"ytd":1161},{"name":"Fail to Keep Right","mtd":0,"ytd":0},{"name":"Fail to Signal","mtd":4,"ytd":54},{"name":"Fail to Stop on Signal","mtd":42,"ytd":435},{"name":"Following Too Closely","mtd":0,"ytd":3},{"name":"Headlights (Defect. or Improper)","mtd":6,"ytd":53},{"name":"Improper Lights","mtd":0,"ytd":3},{"name":"Improper Passing","mtd":9,"ytd":63},{"name":"Improper Turn","mtd":208,"ytd":1476},{"name":"Improper/Missing Plates","mtd":0,"ytd":11},{"name":"Not Giving R of W to Pedes.","mtd":3,"ytd":13},{"name":"Not Giving R of W to Veh.","mtd":2,"ytd":10},{"name":"One Way Street","mtd":0,"ytd":1},{"name":"Pavement Markings","mtd":11,"ytd":157},{"name":"Safety Belt","mtd":105,"ytd":799},{"name":"School Bus, Passing Stopped","mtd":0,"ytd":4},{"name":"Speeding","mtd":9,"ytd":78},{"name":"Spillback","mtd":1,"ytd":6},{"name":"Tinted Windows","mtd":265,"ytd":2921},{"name":"Truck Routes","mtd":10,"ytd":37},{"name":"U-Turn","mtd":2,"ytd":16},{"name":"Uninspected","mtd":11,"ytd":95},{"name":"Uninsured","mtd":125,"ytd":909},{"name":"Unlicensed Operator","mtd":141,"ytd":1170},{"name":"Unregistered","mtd":29,"ytd":204},{"name":"Unsafe Lane Change","mtd":0,"ytd":5},{"name":"Other Movers","mtd":52,"ytd":356}]}