{"precinct":"123rd Precinct","month":"Septembe","violations":[{"name":"Backing Unsafely","mtd":0,"ytd":3},{"name":"Brake Lights (Defect.or Improper)","mtd":52,"ytd":455},{"name":"Bus Lane, Driving in","mtd":0,"ytd":89},{"name":"Cell Phone","mtd":75,"ytd":843},{"name":"Commercial Veh on Pkwy","mtd":0,"ytd":0},{"name":"Defective Brakes","mtd":0,"ytd":10},{"name":"Disobey Sign","mtd":47,"ytd":292},{"name":"Equipment (Other)","mtd":0,"ytd":6},{"name":"Fail to Keep Right","mtd":0,"ytd":3},{"name":"Fail to Signal","mtd":0,"ytd":73},{"name":"Fail to Stop on Signal","mtd":23,"ytd":151},{"name":"Following Too Closely","mtd":2,"ytd":60},{"name":"Headlights (Defect. or Improper)","mtd":53,"ytd":479},{"name":"Improper Lights","mtd":4,"ytd":22},{"name":"Improper Passing","mtd":23,"ytd":268},{"name":"Improper Turn","mtd":12,"ytd":213},{"name":"Improper/Missing Plates","mtd":15,"ytd":72},{"name":"Not Giving R of W to Pedes.","mtd":0,"ytd":3},{"name":"Not Giving R of W to Veh.","mtd":0,"ytd":8},{"name":"One Way Street","mtd":0,"ytd":3},{"name":"Pavement Markings","mtd":27,"ytd":441},{"name":"Safety Belt","mtd":170,"ytd":1542},{"name":"School Bus, Passing Stopped","mtd":0,"ytd":10},{"name":"Speeding","mtd":18,"ytd":663},{"name":"Spillback","mtd":1,"ytd":1},{"name":"Tinted Windows","mtd":61,"ytd":636},{"name":"Truck Routes","mtd":4,"ytd":14},{"name":"U-Turn","mtd":0,"ytd":0},{"name":"Uninspected","mtd":16,"ytd":241},{"name":"Uninsured","mtd":73,"ytd":769},{"name":"Unlicensed Operator","mtd":67,"ytd":620},{"name":"Unregistered","mtd":9,"ytd":113},{"name":"Unsafe Lane Change","mtd":0,"ytd":0},{"name":"Other Movers","mtd":19,"ytd":290}]}