{"precinct":"115th Precinct","month":" January","violations":[{"name":"Backing Unsafely","mtd":2,"ytd":2},{"name":"Brake Lights (Defect.or Improper)","mtd":0,"ytd":0},{"name":"Bus Lane, Driving in","mtd":0,"ytd":0},{"name":"Cell Phone","mtd":188,"ytd":188},{"name":"Commercial Veh on Pkwy","mtd":0,"ytd":0},{"name":"Defective Brakes","mtd":1,"ytd":1},{"name":"Disobey Sign","mtd":167,"ytd":167},{"name":"Equipment (Other)","mtd":8,"ytd":8},{"name":"Fail to Keep Right","mtd":0,"ytd":0},{"name":"Fail to Signal","mtd":13,"ytd":13},{"name":"Fail to Stop on Signal","mtd":73,"ytd":73},{"name":"Following Too Closely","mtd":1,"ytd":1},{"name":"Headlights (Defect. or Improper)","mtd":4,"ytd":4},{"name":"Improper Lights","mtd":53,"ytd":53},{"name":"Improper Passing","mtd":3,"ytd":3},{"name":"Improper Turn","mtd":37,"ytd":37},{"name":"Improper/Missing Plates","mtd":3,"ytd":3},{"name":"Not Giving R of W to Pedes.","mtd":50,"ytd":50},{"name":"Not Giving R of W to Veh.","mtd":0,"ytd":0},{"name":"One Way Street","mtd":15,"ytd":15},{"name":"Pavement Markings","mtd":5,"ytd":5},{"name":"Safety Belt","mtd":267,"ytd":267},{"name":"School Bus, Passing Stopped","mtd":1,"ytd":1},{"name":"Speeding","mtd":19,"ytd":19},{"name":"Spillback","mtd":0,"ytd":0},{"name":"Tinted Windows","mtd":145,"ytd":145},{"name":"Truck Routes","mtd":23,"ytd":23},{"name":"U-Turn","mtd":0,"ytd":0},{"name":"Uninspected","mtd":73,"ytd":73},{"name":"Uninsured","mtd":275,"ytd":275},{"name":"Unlicensed Operator","mtd":361,"ytd":361},{"name":"Unregistered","mtd":23,"ytd":23},{"name":"Unsafe Lane Change","mtd":4,"ytd":4},{"name":"Other Movers","mtd":85,"ytd":85}]}