{"precinct":"67th Precinct","month":"    June","violations":[{"name":"Backing Unsafely","mtd":1,"ytd":8},{"name":"Brake Lights (Defect.or Improper)","mtd":30,"ytd":303},{"name":"Bus Lane, Driving in","mtd":0,"ytd":0},{"name":"Cell Phone","mtd":166,"ytd":828},{"name":"Commercial Veh on Pkwy","mtd":0,"ytd":0},{"name":"Defective Brakes","mtd":0,"ytd":0},{"name":"Disobey Sign","mtd":21,"ytd":102},{"name":"Equipment (Other)","mtd":0,"ytd":0},{"name":"Fail to Keep Right","mtd":0,"ytd":1},{"name":"Fail to Signal","mtd":15,"ytd":89},{"name":"Fail to Stop on Signal","mtd":88,"ytd":530},{"name":"Following Too Closely","mtd":0,"ytd":1},{"name":"Headlights (Defect. or Improper)","mtd":9,"ytd":196},{"name":"Improper Lights","mtd":0,"ytd":1},{"name":"Improper Passing","mtd":8,"ytd":29},{"name":"Improper Turn","mtd":5,"ytd":30},{"name":"Improper/Missing Plates","mtd":0,"ytd":13},{"name":"Not Giving R of W to Pedes.","mtd":15,"ytd":55},{"name":"Not Giving R of W to Veh.","mtd":3,"ytd":26},{"name":"One Way Street","mtd":20,"ytd":28},{"name":"Pavement Markings","mtd":13,"ytd":99},{"name":"Safety Belt","mtd":119,"ytd":755},{"name":"School Bus, Passing Stopped","mtd":0,"ytd":5},{"name":"Speeding","mtd":9,"ytd":78},{"name":"Spillback","mtd":1,"ytd":9},{"name":"Tinted Windows","mtd":184,"ytd":1939},{"name":"Truck Routes","mtd":0,"ytd":31},{"name":"U-Turn","mtd":13,"ytd":206},{"name":"Uninspected","mtd":10,"ytd":81},{"name":"Uninsured","mtd":200,"ytd":1371},{"name":"Unlicensed Operator","mtd":74,"ytd":524},{"name":"Unregistered","mtd":20,"ytd":142},{"name":"Unsafe Lane Change","mtd":1,"ytd":13},{"name":"Other Movers","mtd":100,"ytd":422}]}