{"precinct":"Queens South","month":"    June","violations":[{"name":"Backing Unsafely","mtd":14,"ytd":65},{"name":"Brake Lights (Defect.or Improper)","mtd":308,"ytd":1836},{"name":"Bus Lane, Driving in","mtd":0,"ytd":0},{"name":"Cell Phone","mtd":855,"ytd":5400},{"name":"Commercial Veh on Pkwy","mtd":0,"ytd":1},{"name":"Defective Brakes","mtd":0,"ytd":11},{"name":"Disobey Sign","mtd":986,"ytd":6209},{"name":"Equipment (Other)","mtd":172,"ytd":579},{"name":"Fail to Keep Right","mtd":1,"ytd":8},{"name":"Fail to Signal","mtd":44,"ytd":296},{"name":"Fail to Stop on Signal","mtd":211,"ytd":1718},{"name":"Following Too Closely","mtd":5,"ytd":28},{"name":"Headlights (Defect. or Improper)","mtd":114,"ytd":911},{"name":"Improper Lights","mtd":42,"ytd":455},{"name":"Improper Passing","mtd":31,"ytd":191},{"name":"Improper Turn","mtd":634,"ytd":4137},{"name":"Improper/Missing Plates","mtd":11,"ytd":100},{"name":"Not Giving R of W to Pedes.","mtd":87,"ytd":531},{"name":"Not Giving R of W to Veh.","mtd":31,"ytd":158},{"name":"One Way Street","mtd":6,"ytd":74},{"name":"Pavement Markings","mtd":196,"ytd":1227},{"name":"Safety Belt","mtd":1446,"ytd":7571},{"name":"School Bus, Passing Stopped","mtd":4,"ytd":36},{"name":"Speeding","mtd":228,"ytd":865},{"name":"Spillback","mtd":8,"ytd":52},{"name":"Tinted Windows","mtd":805,"ytd":8954},{"name":"Truck Routes","mtd":67,"ytd":264},{"name":"U-Turn","mtd":49,"ytd":232},{"name":"Uninspected","mtd":90,"ytd":571},{"name":"Uninsured","mtd":629,"ytd":3891},{"name":"Unlicensed Operator","mtd":632,"ytd":3845},{"name":"Unregistered","mtd":86,"ytd":540},{"name":"Unsafe Lane Change","mtd":11,"ytd":76},{"name":"Other Movers","mtd":322,"ytd":1861}]}